tests/__init__.py
tests/conftest.py
tests/test_async.py
tests/test_concurrency.py
tests/test_decorators.py
tests/test_integration.py
tests/test_mcp_hidden_context.py
tests/test_mcp_persistent.py
tests/test_mcp_tools.py
tests/test_models.py
tests/test_openapi_tools.py
tests/test_registry.py
tests/test_retry.py
tests/test_to_markdown.py
tests/test_utils.py
tests/test_validation.py
tests/utils/__init__.py
tests/utils/assertion.py
vaul/__init__.py
vaul/decorators.py
vaul/mcp.py
vaul/models.py
vaul/openapi.py
vaul/registry.py
vaul/utils.py
vaul/validation.py
vaul-1.1.2.dist-info/licenses/LICENSE.txt
vaul-1.1.2.dist-info/METADATA
vaul-1.1.2.dist-info/WHEEL
vaul-1.1.2.dist-info/top_level.txt
vaul-1.1.2.dist-info/RECORD
