Metadata-Version: 2.4
Name: vaul
Version: 1.1.2
Summary: A lightweight Python library for building agentic actions and workflows.
Author: Spencer Porter
Requires-Python: >=3.10
License-File: LICENSE.txt
Requires-Dist: pydantic>=2.6.4
Requires-Dist: pandas>=2.0.0
Requires-Dist: tabulate>=0.9.0
Requires-Dist: pyyaml>=6.0
Requires-Dist: requests>=2.0
Requires-Dist: mcp>=1.0.0
Requires-Dist: nest-asyncio>=1.5.0
Dynamic: author
Dynamic: description
Dynamic: description-content-type
Dynamic: license-file
Dynamic: requires-dist
Dynamic: requires-python
Dynamic: summary
